{
    "episode_number": 813,
    "title": "FLOSS Weekly Episode 813: Turn Off The Internet",
    "date": "2024-12-11",
    "summary": "This week, Jonathan Bennett, Simon Phipps, and Aaron Newcomb chat about retrocomputing, Open Source AI, and … politics? How did that combination of topics come about? Watch to find out!",
    "guests": [],
    "related_links": [],
    "source_url": "https://hackaday.com/2024/12/11/floss-weekly-episode-813-turn-off-the-internet/",
    "media": {
        "audio": "https://traffic.libsyn.com/b27a1a7a-dbb9-4922-ac3e-601e2d6ca1e1/FLOSS-813.mp3",
        "video": "https://www.youtube.com/embed/RDRR4ti-zdQ?feature=oembed"
    }
}