{
    "episode_number": 749,
    "title": "FLOSS Weekly 749: That's In Chapter Three",
    "date": "2023-09-13",
    "summary": "Writing a tech book is easy if you start with the proper guidance. Doc Searls and Jonathan Bennett get that guidance and much more from Kyle Rankin, author of How to Write a Tech Book.\nDownload or subscribe to this show at https://twit.tv/shows/floss-weekly\nThink your open source project should be on FLOSS Weekly? Email floss@twit.tv.\nThanks to Lullabot's Jeff Robbins, web designer and musician, for our theme music.\nGet episodes ad-free with Club TWiT at https://twit.tv/clubtwit",
    "guests": [
        "Kyle Rankin"
    ],
    "source_url": "https://twit.tv/shows/floss-weekly/episodes/749",
    "media": {
        "audio": "https://cdn.twit.tv/audio/floss/floss0749/floss0749.mp3",
        "video": "https://cdn.twit.tv/video/floss/floss0749/floss0749_h264m_1920x1080.mp4"
    }
}